fnv_hash_fast-1.5.0.dist-info/RECORD
fnv_hash_fast-1.5.0.dist-info/LICENSE
fnv_hash_fast-1.5.0.dist-info/WHEEL
fnv_hash_fast-1.5.0.dist-info/METADATA
fnv_hash_fast/fnv_wrapper.h
fnv_hash_fast/__init__.py
fnv_hash_fast/fnv_impl.py
fnv_hash_fast/_fnv_impl.cpython-311-darwin.so
fnv_hash_fast/py.typed
fnv_hash_fast/_fnv_impl.pyx
