Metadata-Version: 2.3
Name: fnv-hash-fast
Version: 1.5.0
Summary: A fast version of fnv1a
License: MIT
Author: J. Nick Koston
Author-email: nick@koston.org
Requires-Python: >=3.10,<4.0
Classifier: Development Status :: 5 - Production/Stable
Classifier: Intended Audience :: Developers
Classifier: License :: OSI Approved :: MIT License
Classifier: Natural Language :: English
Classifier: Operating System :: OS Independent
Classifier: Programming Language :: Python :: 3
Classifier: Programming Language :: Python :: 3.10
Classifier: Programming Language :: Python :: 3.11
Classifier: Programming Language :: Python :: 3.12
Classifier: Programming Language :: Python :: 3.13
Classifier: Topic :: Software Development :: Libraries
Requires-Dist: fnvhash (>=0.1.0,<0.2.0)
Project-URL: Bug Tracker, https://github.com/bluetooth-devices/fnv-hash-fast/issues
Project-URL: Changelog, https://github.com/bluetooth-devices/fnv-hash-fast/blob/main/CHANGELOG.md
Project-URL: Repository, https://github.com/bluetooth-devices/fnv-hash-fast
